build/lib/build/lib/build/lib/cmdliner/__init__.py
build/lib/build/lib/build/lib/cmdliner/__main__.py
build/lib/build/lib/build/lib/cmdliner/application.py
build/lib/build/lib/build/lib/cmdliner/command.py
build/lib/build/lib/build/lib/cmdliner/minimal.py
build/lib/build/lib/build/lib/cmdliner/print.py
build/lib/build/lib/build/lib/cmdliner/singleton.py
build/lib/build/lib/build/lib/cmdliner/spec.py
build/lib/build/lib/build/lib/cmdliner/usage_help.py
build/lib/build/lib/build/lib/cmdliner/version.py
build/lib/build/lib/build/lib/tests/test_version.py
build/lib/build/lib/cmdliner/__init__.py
build/lib/build/lib/cmdliner/__main__.py
build/lib/build/lib/cmdliner/application.py
build/lib/build/lib/cmdliner/command.py
build/lib/build/lib/cmdliner/minimal.py
build/lib/build/lib/cmdliner/print.py
build/lib/build/lib/cmdliner/singleton.py
build/lib/build/lib/cmdliner/spec.py
build/lib/build/lib/cmdliner/usage_help.py
build/lib/build/lib/cmdliner/version.py
build/lib/build/lib/cmdliner/tests/test_minimal.py
build/lib/build/lib/cmdliner/tests/test_version.py
build/lib/build/lib/tests/test_version.py
build/lib/cmdliner/__init__.py
build/lib/cmdliner/__main__.py
build/lib/cmdliner/application.py
build/lib/cmdliner/command.py
build/lib/cmdliner/minimal.py
build/lib/cmdliner/print.py
build/lib/cmdliner/singleton.py
build/lib/cmdliner/spec.py
build/lib/cmdliner/usage_help.py
build/lib/cmdliner/version.py
build/lib/cmdliner/tests/test_minimal.py
build/lib/cmdliner/tests/test_version.py
build/lib/tests/test_version.py
cmdliner/__init__.py
cmdliner/__main__.py
cmdliner/application.py
cmdliner/command.py
cmdliner/minimal.py
cmdliner/print.py
cmdliner/singleton.py
cmdliner/spec.py
cmdliner/usage_help.py
cmdliner/version.py
cmdliner/tests/test_args.py
cmdliner/tests/test_minimal.py
cmdliner/tests/test_version.py
tests/test_version.py
cmdliner-0.0.2.dist-info/LICENSE
cmdliner-0.0.2.dist-info/METADATA
cmdliner-0.0.2.dist-info/WHEEL
cmdliner-0.0.2.dist-info/entry_points.txt
cmdliner-0.0.2.dist-info/top_level.txt
cmdliner-0.0.2.dist-info/RECORD
