Metadata-Version: 2.1
Name: cmdliner
Version: 0.0.2
Summary: Command line builder library
Home-page: https://github.com/joaompinto/cmdliner
Author: João Pinto
Author-email: lamego.pinto@gmail.com
License: MIT
Platform: UNKNOWN
Requires-Dist: attrs
